MANIFEST.in
README
setup.py
bin/pytest
docs/Makefile
docs/__init__.py
docs/conf.py
docs/examples.rst
docs/index.rst
docs/md.abc.rst
docs/md.annotate.rst
docs/md.expect.rst
docs/md.fluid.rst
docs/md.rst
docs/md.stm.rst
docs/md.test.rst
docs/scripts.rst
docs/examples/__init__.py
docs/examples/annotate.rst
docs/examples/django_request.py
docs/examples/expected.py
docs/examples/fluid-bindings.rst
docs/examples/fluidprint.py
docs/examples/request_middleware.py
docs/examples/stm.rst
docs/examples/stm_shelf.py
md/__init__.py
md/abc.py
md/expect.py
md/fluid.py
md/test.py
md.py.egg-info/PKG-INFO
md.py.egg-info/SOURCES.txt
md.py.egg-info/dependency_links.txt
md.py.egg-info/requires.txt
md.py.egg-info/top_level.txt
md/annotate/__init__.py
md/annotate/annotate.py
md/annotate/compiler.py
md/annotate/decorate.py
md/annotate/gensym.py
md/annotate/util.py
md/stm/__init__.py
md/stm/cursor.py
md/stm/interfaces.py
md/stm/journal.py
md/stm/log.py
md/stm/meronymy.py
md/stm/transaction.py
tests/__init__.py