Metadata-Version: 1.0
Name: md.py
Version: 0.2
Summary: A collection of Python utilities.
Home-page: http://thisismedium.com/labs/mdpy/
Author: Medium
Author-email: labs@thisismedium.com
License: BSD
Keywords: utilities transaction transactions fluid dynamic
Platform: UNKNOWN
Classifier: Development Status :: 3 - Alpha
Classifier: Intended Audience :: Developers
Classifier: License :: OSI Approved :: BSD License
Classifier: Operating System :: OS Independent
Classifier: Programming Language :: Python
Classifier: Topic :: Utilities
